smex/__init__.py
smex/pissbot.py
smex/smex.py
smex/smtests.py
smex-0.2.dist-info/DESCRIPTION.rst
smex-0.2.dist-info/METADATA
smex-0.2.dist-info/RECORD
smex-0.2.dist-info/WHEEL
smex-0.2.dist-info/metadata.json
smex-0.2.dist-info/top_level.txt
