Metadata-Version: 2.0
Name: smex
Version: 0.2
Summary: A little state machine
Home-page: https://github.com/enthus1ast/smex
Author: David Krause
Author-email: david@klangfragment.de
License: UNKNOWN
Platform: UNKNOWN
